{"format_version":"1.12","minecraft:recipe_shaped":{"unlock":[{"item":"minecraft:dragon_egg"}],"description":{"identifier":"hfrlc:elemental_sword"},"tags":["crafting_table"],"pattern":["WGX","EDR","FVQ"],"key":{"G":{"item":"hfrlc:dragon_skull"},"W":{"item":"hfrlc:light_sword"},"X":{"item":"hfrlc:earth_sword"},"E":{"item":"hfrlc:ice_dragon_blood"},"D":{"item":"hfrlc:thunder_sword"},"R":{"item":"hfrlc:flaming_dragon_blood"},"F":{"item":"hfrlc:lava_sword"},"V":{"item":"minecraft:dragon_egg"},"Q":{"item":"hfrlc:ocean_sword"}},"result":{"item":"hfrlc:elemental_sword"}}}