{"format_version":"1.21.50","minecraft:item":{"description":{"identifier":"hfrlc:purple_heather","menu_category":{"category":"nature"}},"components":{"minecraft:icon":"hfrlc_purple_heather","minecraft:display_name":{"value":"tile.hfrlc:purple_heather.name"},"minecraft:block_placer":{"block":"hfrlc:purple_heather","replace_block_item":true,"use_on":["minecraft:grass_block","minecraft:dirt","minecraft:podzol","minecraft:mycelium","minecraft:dirt_with_roots","minecraft:moss_block","minecraft:mud","minecraft:farmland","minecraft:muddy_mangrove_roots"]}}}}