{"format_version":"1.21.80","minecraft:block":{"description":{"identifier":"hfrlc:pumpkin","menu_category":{"category":"none"},"traits":{"minecraft:placement_direction":{"enabled_states":["minecraft:cardinal_direction"]}},"states":{"hfrlc:pumpkin_spawner":[false,true]}},"components":{"tag:hfrlc:foliage":{},"tag:plant":{},"tag:fertilize_area":{},"tag:minecraft:is_axe_item_destructible":{},"minecraft:destructible_by_mining":{"seconds_to_destroy":1.2,"item_specific_speeds":[{"item":{"tags":"query.all_tags('minecraft:is_axe')"},"destroy_speed":0.75},{"item":{"tags":"query.all_tags('minecraft:is_axe', 'minecraft:stone_tier')"},"destroy_speed":0.398438},{"item":{"tags":"query.all_tags('minecraft:is_axe', 'minecraft:iron_tier')"},"destroy_speed":0.234375},{"item":{"tags":"query.all_tags('minecraft:is_axe', 'minecraft:golden_tier')"},"destroy_speed":0.140625},{"item":{"tags":"query.all_tags('minecraft:is_axe', 'minecraft:diamond_tier')"},"destroy_speed":0.1875},{"item":{"tags":"query.all_tags('minecraft:is_axe', 'minecraft:netherite_tier')"},"destroy_speed":0.164063}]},"minecraft:light_dampening":0,"minecraft:collision_box":{"origin":[-8,0,-8],"size":[16,14,16]},"minecraft:selection_box":{"origin":[-8,0,-8],"size":[16,14,16]},"minecraft:loot":"loot_tables/blocks/pumpkin.json","minecraft:geometry":{"identifier":"geometry.pumpkin"},"minecraft:material_instances":{"*":{"texture":"hfrlc_pumpkin_side","render_method":"alpha_test_single_sided_to_opaque","ambient_occlusion":true,"face_dimming":true},"top":{"texture":"hfrlc_pumpkin_top","render_method":"alpha_test_single_sided_to_opaque","ambient_occlusion":true,"face_dimming":true},"side":{"texture":"hfrlc_pumpkin_side","render_method":"alpha_test_single_sided_to_opaque","ambient_occlusion":true,"face_dimming":true},"bottom":{"texture":"hfrlc_pumpkin_bottom","render_method":"alpha_test_single_sided_to_opaque","ambient_occlusion":true,"face_dimming":true},"root":{"texture":"hfrlc_pumpkin_root","render_method":"alpha_test_single_sided_to_opaque","ambient_occlusion":true,"face_dimming":true}}},"permutations":[{"condition":"query.block_state('minecraft:cardinal_direction') == 'south'","components":{"minecraft:transformation":{"rotation":[0,180,0]}}},{"condition":"query.block_state('minecraft:cardinal_direction') == 'east'","components":{"minecraft:transformation":{"rotation":[0,-90,0]}}},{"condition":"query.block_state('minecraft:cardinal_direction') == 'west'","components":{"minecraft:transformation":{"rotation":[0,90,0]}}},{"condition":"query.block_state('hfrlc:pumpkin_spawner')","components":{"minecraft:custom_components":["hfrlc:pumpkin_spawner"],"minecraft:tick":{"interval_range":[20,20],"looping":true}}}]}}